typegpt_light/__init__.py
typegpt_light/exceptions.py
typegpt_light/openai/__init__.py
typegpt_light/openai/base_chat_completion.py
typegpt_light/openai/exceptions.py
typegpt_light/openai/views.py
typegpt_light/openai/_async/__init__.py
typegpt_light/openai/_async/chat_completion.py
typegpt_light/openai/_async/client.py
typegpt_light/openai/_sync/__init__.py
typegpt_light/openai/_sync/chat_completion.py
typegpt_light/openai/_sync/client.py
typegpt_light/prompt_definition/__init__.py
typegpt_light/prompt_definition/image.py
typegpt_light/prompt_definition/prompt_settings.py
typegpt_light/prompt_definition/prompt_template.py
typegpt_light/utils/__init__.py
typegpt_light/utils/internal_types.py
typegpt_light/utils/utils.py
typegpt_light-0.0.5.dist-info/METADATA
typegpt_light-0.0.5.dist-info/WHEEL
typegpt_light-0.0.5.dist-info/licenses/LICENSE
typegpt_light-0.0.5.dist-info/RECORD
