Metadata-Version: 2.4
Name: typegpt_light
Version: 0.0.5
Summary: TypeGPT Light is a reduced version of TypeGPT that uses OpenAI's built-in structured output, but keeps some nice architecture features of TypeGPT.
Project-URL: Homepage, https://github.com/alexeichhorn/typegpt-light
Project-URL: Repository, https://github.com/alexeichhorn/typegpt-light
Author: Alexander Eichhorn
License: MIT License
License-File: LICENSE
Classifier: License :: OSI Approved :: MIT License
Classifier: Operating System :: OS Independent
Classifier: Programming Language :: Python :: 3
Requires-Python: >=3.10
Requires-Dist: openai>=1.99.3
Requires-Dist: typing-extensions>=4.1.0
